pyastsim/__init__.py
pyastsim/pyastsim.py
pyastsim-1.2.0.dist-info/METADATA
pyastsim-1.2.0.dist-info/WHEEL
pyastsim-1.2.0.dist-info/entry_points.txt
pyastsim-1.2.0.dist-info/top_level.txt
pyastsim-1.2.0.dist-info/RECORD
