Metadata-Version: 2.1
Name: pyastsim
Version: 1.2.0
Summary: Detect similarities between Python source files
Home-page: https://github.com/jncraton/pyastsim
Author: Jon Craton
Author-email: jon@joncraton.com
License: UNKNOWN
Platform: UNKNOWN
Classifier: Programming Language :: Python :: 3
Classifier: License :: OSI Approved :: MIT License
Classifier: Operating System :: OS Independent
Requires-Python: >=3.6
Requires-Dist: astunparse
Requires-Dist: editdistance
